{"assets":{"DA31E9A99B30845C2946BA5A35A0F41D":{"type":"texture","index":5,"assetRequest":{"type":"slide","state":"incoming","slide":"B360D664-7A8A-49BE-8BF4-E3DC09C2E596"},"url":"assets/DA31E9A99B30845C2946BA5A35A0F41D.svg","width":1024,"height":768},"2CEDC5E87486AECBC834D75246096505":{"type":"texture","index":4,"assetRequest":{"type":"slide","state":"outgoing","slide":"8EC57AFC-4C03-423E-85E0-8F2C9024C7D0"},"url":"assets/2CEDC5E87486AECBC834D75246096505.svg","width":1024,"height":768}},"events":[{"effects":[{"beginTime":0,"baseLayer":{"animations":[],"initialState":{"affineTransform":[1,0,0,1,0,0],"masksToBounds":true,"rotation":0,"scale":1,"position":{"pointX":512,"pointY":384},"width":1024,"sublayerTransform":[1,0,0,0,0,1,0,0,0,0,1,0,0,0,0,1],"contentsRect":{"y":0,"x":0,"width":1,"height":1},"opacity":1,"edgeAntialiasingMask":0,"height":768,"hidden":false,"anchorPoint":{"pointX":0.5,"pointY":0.5}},"objectID":"0","layers":[{"animations":[],"initialState":{"affineTransform":[1,0,0,1,0,0],"masksToBounds":false,"rotation":0,"scale":1,"position":{"pointX":512,"pointY":384},"width":1024,"sublayerTransform":[1,0,0,0,0,1,0,0,0,0,1,-0.0004922987690640373,0,0,0,1],"contentsRect":{"y":0,"x":0,"width":1,"height":1},"opacity":1,"edgeAntialiasingMask":15,"height":768,"hidden":false,"anchorPoint":{"pointX":0.5,"pointY":0.5}},"layers":[{"animations":[],"layers":[],"initialState":{"affineTransform":[1,0,0,1,0,0],"masksToBounds":false,"rotation":0,"scale":1,"position":{"pointX":512,"pointY":384},"width":1024,"sublayerTransform":[1,0,0,0,0,1,0,0,0,0,1,0,0,0,0,1],"contentsRect":{"y":0,"x":0,"width":1,"height":1},"opacity":1,"edgeAntialiasingMask":0,"height":768,"hidden":false,"anchorPoint":{"pointX":0.5,"pointY":0.5}},"texture":"DA31E9A99B30845C2946BA5A35A0F41D"},{"animations":[{"from":{"scalar":false},"beginTime":0,"repeatCount":0,"fillMode":"both","property":"hidden","duration":0.01,"to":{"scalar":true}}],"layers":[],"initialState":{"affineTransform":[1,0,0,1,0,0],"masksToBounds":false,"rotation":0,"scale":1,"position":{"pointX":512,"pointY":384},"width":1024,"sublayerTransform":[1,0,0,0,0,1,0,0,0,0,1,0,0,0,0,1],"contentsRect":{"y":0,"x":0,"width":1,"height":1},"opacity":1,"edgeAntialiasingMask":0,"height":768,"hidden":false,"anchorPoint":{"pointX":0.5,"pointY":0.5}},"texture":"2CEDC5E87486AECBC834D75246096505"}]}]},"effects":[],"duration":0.01,"type":"transition","name":"none","objectID":"0"}],"automaticPlay":false,"hyperlinks":[{"url":"mailto:codetojoy@gmail.com","targetRectangle":{"y":408.53125,"x":109.9999995231628,"width":369.216,"height":81}}],"accessibility":[{"text":"ABOUT","targetRectangle":{"y":54,"x":75,"width":190.2719995708466,"height":66}},{"text":"Chalk_Line_10x7.png","targetRectangle":{"y":28,"x":31,"width":962,"height":691}},{"text":"@30_for_60","targetRectangle":{"y":278.53125,"x":109.9999995231628,"width":196.6319999999999,"height":49}},{"text":"@codetojoy","targetRectangle":{"y":327.53125,"x":109.9999995231628,"width":195.3,"height":81}},{"text":"codetojoy@gmail.com","targetRectangle":{"y":408.53125,"x":109.9999995231628,"width":369.216,"height":81}}],"baseLayer":{"animations":[],"initialState":{"affineTransform":[1,0,0,1,0,0],"masksToBounds":true,"rotation":0,"scale":1,"position":{"pointX":512,"pointY":384},"width":1024,"sublayerTransform":[1,0,0,0,0,1,0,0,0,0,1,0,0,0,0,1],"contentsRect":{"y":0,"x":0,"width":1,"height":1},"opacity":1,"edgeAntialiasingMask":0,"height":768,"hidden":false,"anchorPoint":{"pointX":0.5,"pointY":0.5}},"objectID":"0","layers":[{"animations":[],"initialState":{"affineTransform":[1,0,0,1,0,0],"masksToBounds":false,"rotation":0,"scale":1,"position":{"pointX":512,"pointY":384},"width":1024,"sublayerTransform":[1,0,0,0,0,1,0,0,0,0,1,-0.0004922987690640373,0,0,0,1],"contentsRect":{"y":0,"x":0,"width":1,"height":1},"opacity":1,"edgeAntialiasingMask":15,"height":768,"hidden":false,"anchorPoint":{"pointX":0.5,"pointY":0.5}},"layers":[{"animations":[],"layers":[],"initialState":{"affineTransform":[1,0,0,1,0,0],"masksToBounds":false,"rotation":0,"scale":1,"position":{"pointX":512,"pointY":384},"width":1024,"sublayerTransform":[1,0,0,0,0,1,0,0,0,0,1,0,0,0,0,1],"contentsRect":{"y":0,"x":0,"width":1,"height":1},"opacity":1,"edgeAntialiasingMask":0,"height":768,"hidden":false,"anchorPoint":{"pointX":0.5,"pointY":0.5}},"texture":"2CEDC5E87486AECBC834D75246096505"}]}]}}]}